cartoframes/__init__.py
cartoframes/_version.py
cartoframes/exceptions.py
cartoframes/analysis/__init__.py
cartoframes/analysis/grid.py
cartoframes/assets/init.js.j2
cartoframes/assets/init_layout.js.j2
cartoframes/assets/src/bundle.js
cartoframes/assets/src/constants.js
cartoframes/assets/src/index.js
cartoframes/assets/src/layers.js
cartoframes/assets/src/legends.js
cartoframes/assets/src/map.js
cartoframes/assets/src/utils.js
cartoframes/assets/src/widgets.js
cartoframes/assets/src/errors/display.js
cartoframes/assets/src/errors/parse.js
cartoframes/assets/src/map/SourceFactory.js
cartoframes/assets/src/map/interactivity.js
cartoframes/assets/src/map/popups.js
cartoframes/assets/style/common.html.j2
cartoframes/assets/style/error.html.j2
cartoframes/assets/style/layout.html.j2
cartoframes/assets/style/map.html.j2
cartoframes/assets/style/popup.html.j2
cartoframes/assets/style/widgets.html.j2
cartoframes/assets/style/themes/dark.html.j2
cartoframes/assets/style/themes/light.html.j2
cartoframes/assets/templates/iframe.html.j2
cartoframes/assets/templates/error/basic.html.j2
cartoframes/assets/templates/viz/basic.html.j2
cartoframes/assets/templates/viz/footer.html.j2
cartoframes/assets/templates/viz/layout.html.j2
cartoframes/assets/templates/viz/legends.html.j2
cartoframes/assets/templates/viz/legends_layout.html.j2
cartoframes/assets/templates/viz/main.html.j2
cartoframes/assets/templates/viz/main_layout.html.j2
cartoframes/assets/templates/viz/widgets.html.j2
cartoframes/assets/templates/viz/widgets/animation.html.j2
cartoframes/assets/templates/viz/widgets/basic.html.j2
cartoframes/assets/templates/viz/widgets/category.html.j2
cartoframes/assets/templates/viz/widgets/formula.html.j2
cartoframes/assets/templates/viz/widgets/histogram.html.j2
cartoframes/assets/templates/viz/widgets/time-series.html.j2
cartoframes/auth/__init__.py
cartoframes/auth/credentials.py
cartoframes/auth/defaults.py
cartoframes/data/__init__.py
cartoframes/data/clients/__init__.py
cartoframes-1.2.5.dist-info/LICENSE
cartoframes-1.2.5.dist-info/METADATA
cartoframes-1.2.5.dist-info/WHEEL
cartoframes-1.2.5.dist-info/top_level.txt
cartoframes-1.2.5.dist-info/RECORD
