Metadata-Version: 2.1
Name: cartoframes
Version: 1.2.5
Summary: CARTO Python package for data scientists
Home-page: https://github.com/CartoDB/cartoframes
Author: CARTO
Author-email: contact@carto.com
License: BSD
Keywords: carto,data,science,maps,spatial,pandas
Platform: UNKNOWN
Classifier: Development Status :: 5 - Production/Stable
Classifier: Intended Audience :: Developers
Classifier: Intended Audience :: Science/Research
Classifier: License :: OSI Approved :: BSD License
Classifier: Programming Language :: Python
Classifier: Programming Language :: Python :: 3
Classifier: Programming Language :: Python :: 3.5
Classifier: Programming Language :: Python :: 3.6
Classifier: Programming Language :: Python :: 3.7
Classifier: Programming Language :: Python :: 3.8
Requires-Python: >=3.5
License-File: LICENSE
Requires-Dist: appdirs (<2.0,>=1.4.3)
Requires-Dist: carto (<2.0,>=1.11.3)
Requires-Dist: geopandas (<1.0,>=0.6.0)
Requires-Dist: jinja2 (<3.0,>=2.10.1)
Requires-Dist: markupsafe (<=2.0.1)
Requires-Dist: pandas (>=0.25.0)
Requires-Dist: semantic-version (<3,>=2.8.0)
Requires-Dist: unidecode (<2.0,>=1.1.0)
Provides-Extra: tests
Requires-Dist: flake8 ; extra == 'tests'
Requires-Dist: pylint ; extra == 'tests'
Requires-Dist: pytest ; extra == 'tests'
Requires-Dist: pytest-mock ; extra == 'tests'
